LICENSE
setup.py
delicolour/__init__.py
delicolour/adjustment_controls.py
delicolour/app_model.py
delicolour/big_colour.py
delicolour/colour.py
delicolour/colour_text_entry.py
delicolour/config.py
delicolour/css_hex_entry.py
delicolour/css_rgb_entry.py
delicolour/fav_colour.py
delicolour/fav_colours.py
delicolour/fine_controls.py
delicolour/main.py
delicolour/main_window.py
delicolour/scale_entry.py
delicolour.egg-info/PKG-INFO
delicolour.egg-info/SOURCES.txt
delicolour.egg-info/dependency_links.txt
delicolour.egg-info/entry_points.txt
delicolour.egg-info/requires.txt
delicolour.egg-info/top_level.txt
delicolour/res/desat-24.png
delicolour/res/moon-24.png
delicolour/res/sat-24.png
delicolour/res/sun-24.png