Metadata-Version: 2.1
Name: delicolour
Version: 1.3.0
Summary: colour finder
Home-page: https://github.com/eepp/delicolour
Author: Philippe Proulx
Author-email: eeppeliteloop@gmail.com
License: UNKNOWN
Platform: UNKNOWN
License-File: LICENSE
